{"name":"URP","slug":"URP","count":1,"postlist":[{"title":"URP源码分析","uid":"23661fa8ae25c981d575d8f076eed3e1","slug":"Rendering/UpdateToURPPipeline/URPSourceCode","date":"2023-04-08T13:32:05.000Z","updated":"2023-10-27T20:19:19.000Z","comments":true,"path":"api/articles/Rendering/UpdateToURPPipeline/URPSourceCode.json","keywords":null,"cover":"https://raw.githubusercontent.com/JBR-Bunjie/JBR-Bunjie/main/back.jpg","text":"URP源码分析 依赖信息： Editor版本：2021.21f1 LTS Shader版本：URP 12.1.10 URP Package总览 首先，当我们下载URP资源时，我们的项目的Package中会出现这些内容： URP资源结构 - com.unity.render-pip...","link":"","photos":[],"count_time":{"symbolsCount":"5.1k","symbolsTime":"5 mins."},"categories":[{"name":"Unity","slug":"Unity","count":17,"path":"api/categories/Unity.json"}],"tags":[{"name":"Unity","slug":"Unity","count":17,"path":"api/tags/Unity.json"},{"name":"Shader","slug":"Shader","count":33,"path":"api/tags/Shader.json"},{"name":"URP","slug":"URP","count":1,"path":"api/tags/URP.json"}],"author":{"name":"JBR_Bunjie","slug":"blog-author","avatar":"https://avatars.githubusercontent.com/u/90251718?v=4","link":"/","description":"仿生程序员会在光环上遇见AI乐正绫吗？","socials":{"github":"","twitter":"","stackoverflow":"","wechat":"","qq":"","weibo":"","zhihu":"","csdn":"","juejin":"","customs":{"bilibili":{"icon":"/svg/bilibili-fill.svg","link":"https://space.bilibili.com/415377461"},"github":{"icon":"/svg/social_github.svg","link":"https://github.com/JBR-Bunjie"}}}}}]}